sparqlin/__init__.py
sparqlin/etl.py
sparqlin/main.py
sparqlin/logging/__init__.py
sparqlin/logging/logger_config.py
sparqlin/testing/__init__.py
sparqlin/testing/base_test_config.py
sparqlin/testing/fixtures.py
sparqlin/testing/helpers.py
tests/__init__.py
tests/test_etl.py
tests/test_wrapper.py
tests/testing/__init__.py
tests/testing/test_base_test_config.py
tests/testing/test_get_spark_dataframe.py
sparqlin-0.1.16.dist-info/LICENSE
sparqlin-0.1.16.dist-info/METADATA
sparqlin-0.1.16.dist-info/WHEEL
sparqlin-0.1.16.dist-info/entry_points.txt
sparqlin-0.1.16.dist-info/top_level.txt
sparqlin-0.1.16.dist-info/RECORD
