Metadata-Version: 2.1
Name: sparqlin
Version: 0.1.16
Summary: Spark SQL framework for Databricks jobs
Home-page: https://gitlab.com/rokorolev/sparqlin
Author: Roman Korolev
Author-email: spark_development@yahoo.com
License: MIT
Classifier: Programming Language :: Python :: 3
Classifier: License :: OSI Approved :: MIT License
Classifier: Operating System :: OS Independent
Classifier: Topic :: Software Development :: Libraries :: Python Modules
Requires-Python: >=3.11
License-File: LICENSE
Requires-Dist: pytest
Requires-Dist: pyspark>=3.5.0
Requires-Dist: pyyaml
Requires-Dist: psutil
Requires-Dist: gitpython
